Workbook

Sheet APRESENTAÇÃO
B1: COMPOSIÇÃO DE PREÇO DE VENDA
B2: DE PEÇAS IMPRESSAS EM 3D
L22: VISITE A LOJA
J24: www.promakers.com.br
A32: REFERÊNCIAS:
B33: SEBRAE PR | E33: https://www.youtube.com/watch?v=l4zraPJbcPw&t=1s
B34: CNC KITCHEN | E34: https://www.youtube.com/watch?v=ffg9dArNfCg

Sheet IMPRESSORAS
B2: IMPRESSORA | C2: PREÇO (R$) | D2: MANUTENÇÃO (R$) | E2: VIDA ÚTIL (h) | F2: CONSUMO (kW) | G2: DEPRECIAÇÃO (R$/h)
B3: Kobra | C3: 3300 | D3: =C3*0.25 -> 825 | E3: 5000 | F3: 0.125 | G3: =IF(E3>0,(C3+D3)/E3,) -> 0.825
G4: =IF(E4>0,(C4+D4)/E4,) -> 0
G5: =IF(E5>0,(C5+D5)/E5,) -> 0
G6: =IF(E6>0,(C6+D6)/E6,) -> 0
G7: =IF(E7>0,(C7+D7)/E7,) -> 0
G8: =IF(E8>0,(C8+D8)/E8,) -> 0
G9: =IF(E9>0,(C9+D9)/E9,) -> 0
G10: =IF(E10>0,(C10+D10)/E10,) -> 0
G11: =IF(E11>0,(C11+D11)/E11,) -> 0
G12: =IF(E12>0,(C12+D12)/E12,) -> 0
G13: =IF(E13>0,(C13+D13)/E13,) -> 0
G14: =IF(E14>0,(C14+D14)/E14,) -> 0
G15: =IF(E15>0,(C15+D15)/E15,) -> 0
... G51: =IF(E51>0,(C51+D51)/E51,) -> 0

Sheet MATERIAIS
B2: MARCA | C2: CUSTO/ROLO (R$) | D2: PESO/ROLO (kg) | E2: CUSTO/PESO (R$/kg)
B3: ABS (Genérico) | C3: 90 | D3: 1 | E3: =IF(D3>0,C3/D3,) -> 90
B4: PLA | C4: 119 | D4: 1 | E4: =IF(D4>0,C4/D4,) -> 119
B5: PETG (Benser) | C5: 119 | D5: 1 | E5: =IF(D5>0,C5/D5,) -> 119
B6: PLA voolt | C6: 105 | D6: 1 | E6: =IF(D6>0,C6/D6,) -> 105
B7: abs voolt | C7: 80 | D7: 1 | E7: =IF(D7>0,C7/D7,) -> 80
B8: PLA caro | C8: 135 | D8: 1 | E8: =IF(D8>0,C8/D8,) -> 135
E9: =IF(D9>0,C9/D9,) -> 0
E10: =IF(D10>0,C10/D10,) -> 0
E11: =IF(D11>0,C11/D11,) -> 0
E12: =IF(D12>0,C12/D12,) -> 0
E13: =IF(D13>0,C13/D13,) -> 0
E14: =IF(D14>0,C14/D14,) -> 0
E15: =IF(D15>0,C15/D15,) -> 0
E16: =IF(D16>0,C16/D16,) -> 0
E17: =IF(D17>0,C17/D17,) -> 0
E18: =IF(D18>0,C18/D18,) -> 0
E19: =IF(D19>0,C19/D19,) -> 0
E20: =IF(D20>0,C20/D20,) -> 0
... E51: =IF(D51>0,C51/D51,) -> 0

Sheet CUSTO DE IMPRESSÃO 3D
B2: MESAS | C2: PESO (g) | D2: MATERIAL | E2: IMPRESSORA | F2: TEMPO DE MÁQUINA | J2: CUSTO MATERIAL | K2: CUSTO MÁQUINA | N2: SUBTOTAL | O2: TOTAL
B3: (PEÇAS) | F3: DIAS | G3: HORAS | H3: MINUTOS | I3: TOTAL (HORAS) | J3: TOTAL | K3: DEPRECIAÇÃO | L3: ELETRICIDADE | M3: TOTAL
I4: =SUM(I5:I15) -> 4.3333333 | J4: =SUM(J5:J15) -> 6.345 | K4: =SUM(K5:K15) -> 3.575 | L4: =SUM(L5:L15) -> 0.4875 | M4: =SUM(M5:M15) -> 4.0625 | N4: =M4+J4 -> 10.4075 | O4: =N4/(1-D21/100)+D23 -> 12.244118
B5: aranha | C5: 47 | D5: PLA caro | E5: Kobra | G5: 4 | H5: 20 | I5: =H5/60+G5+F5*24 -> 4.3333333 | J5: =IF(D5<>"",C5/1000*VLOOKUP(D5,MATERIAIS!$B$3:$E$51,4,FALSE),0) -> 6.345 | K5: =IF(E5<>"",I5*VLOOKUP(E5,IMPRESSORAS!$B$3:$G$51,6,FALSE),0) -> 3.575 | L5: =IF(E5<>"",I5*$D$20*VLOOKUP(E5,IMPRESSORAS!$B$3:$G$51,5,FALSE),0) -> 0.4875 | M5: =SUM(K5:L5) -> 4.0625
D6: PLA voolt | E6: Kobra | I6: =H6/60+G6+F6*24 -> 0 | J6: =IF(D6<>"",C6/1000*VLOOKUP(D6,MATERIAIS!$B$3:$E$51,4,FALSE),0) -> 0 | K6: =IF(E6<>"",I6*VLOOKUP(E6,IMPRESSORAS!$B$3:$G$51,6,FALSE),0) -> 0 | L6: =IF(E6<>"",I6*$D$20*VLOOKUP(E6,IMPRESSORAS!$B$3:$G$51,5,FALSE),0) -> 0 | M6: =SUM(K6:L6) -> 0
D7: PLA voolt | E7: Kobra | I7: =H7/60+G7+F7*24 -> 0 | J7: =IF(D7<>"",C7/1000*VLOOKUP(D7,MATERIAIS!$B$3:$E$51,4,FALSE),0) -> 0 | K7: =IF(E7<>"",I7*VLOOKUP(E7,IMPRESSORAS!$B$3:$G$51,6,FALSE),0) -> 0 | L7: =IF(E7<>"",I7*$D$20*VLOOKUP(E7,IMPRESSORAS!$B$3:$G$51,5,FALSE),0) -> 0 | M7: =SUM(K7:L7) -> 0
D8: PLA voolt | E8: Kobra | I8: =H8/60+G8+F8*24 -> 0 | J8: =IF(D8<>"",C8/1000*VLOOKUP(D8,MATERIAIS!$B$3:$E$51,4,FALSE),0) -> 0 | K8: =IF(E8<>"",I8*VLOOKUP(E8,IMPRESSORAS!$B$3:$G$51,6,FALSE),0) -> 0 | L8: =IF(E8<>"",I8*$D$20*VLOOKUP(E8,IMPRESSORAS!$B$3:$G$51,5,FALSE),0) -> 0 | M8: =SUM(K8:L8) -> 0
D9: PLA voolt | E9: Kobra | I9: =H9/60+G9+F9*24 -> 0 | J9: =IF(D9<>"",C9/1000*VLOOKUP(D9,MATERIAIS!$B$3:$E$51,4,FALSE),0) -> 0 | K9: =IF(E9<>"",I9*VLOOKUP(E9,IMPRESSORAS!$B$3:$G$51,6,FALSE),0) -> 0 | L9: =IF(E9<>"",I9*$D$20*VLOOKUP(E9,IMPRESSORAS!$B$3:$G$51,5,FALSE),0) -> 0 | M9: =SUM(K9:L9) -> 0
D10: PLA voolt | E10: Kobra | I10: =H10/60+G10+F10*24 -> 0 | J10: =IF(D10<>"",C10/1000*VLOOKUP(D10,MATERIAIS!$B$3:$E$51,4,FALSE),0) -> 0 | K10: =IF(E10<>"",I10*VLOOKUP(E10,IMPRESSORAS!$B$3:$G$51,6,FALSE),0) -> 0 | L10: =IF(E10<>"",I10*$D$20*VLOOKUP(E10,IMPRESSORAS!$B$3:$G$51,5,FALSE),0) -> 0 | M10: =SUM(K10:L10) -> 0
D11: PLA voolt | E11: Kobra | I11: =H11/60+G11+F11*24 -> 0 | J11: =IF(D11<>"",C11/1000*VLOOKUP(D11,MATERIAIS!$B$3:$E$51,4,FALSE),0) -> 0 | K11: =IF(E11<>"",I11*VLOOKUP(E11,IMPRESSORAS!$B$3:$G$51,6,FALSE),0) -> 0 | L11: =IF(E11<>"",I11*$D$20*VLOOKUP(E11,IMPRESSORAS!$B$3:$G$51,5,FALSE),0) -> 0 | M11: =SUM(K11:L11) -> 0
D12: PLA voolt | E12: Kobra | I12: =H12/60+G12+F12*24 -> 0 | J12: =IF(D12<>"",C12/1000*VLOOKUP(D12,MATERIAIS!$B$3:$E$51,4,FALSE),0) -> 0 | K12: =IF(E12<>"",I12*VLOOKUP(E12,IMPRESSORAS!$B$3:$G$51,6,FALSE),0) -> 0 | L12: =IF(E12<>"",I12*$D$20*VLOOKUP(E12,IMPRESSORAS!$B$3:$G$51,5,FALSE),0) -> 0 | M12: =SUM(K12:L12) -> 0
D13: PLA voolt | E13: Kobra | I13: =H13/60+G13+F13*24 -> 0 | J13: =IF(D13<>"",C13/1000*VLOOKUP(D13,MATERIAIS!$B$3:$E$51,4,FALSE),0) -> 0 | K13: =IF(E13<>"",I13*VLOOKUP(E13,IMPRESSORAS!$B$3:$G$51,6,FALSE),0) -> 0 | L13: =IF(E13<>"",I13*$D$20*VLOOKUP(E13,IMPRESSORAS!$B$3:$G$51,5,FALSE),0) -> 0 | M13: =SUM(K13:L13) -> 0
D14: PLA voolt | E14: Kobra | I14: =H14/60+G14+F14*24 -> 0 | J14: =IF(D14<>"",C14/1000*VLOOKUP(D14,MATERIAIS!$B$3:$E$51,4,FALSE),0) -> 0 | K14: =IF(E14<>"",I14*VLOOKUP(E14,IMPRESSORAS!$B$3:$G$51,6,FALSE),0) -> 0 | L14: =IF(E14<>"",I14*$D$20*VLOOKUP(E14,IMPRESSORAS!$B$3:$G$51,5,FALSE),0) -> 0 | M14: =SUM(K14:L14) -> 0
D15: PLA voolt | E15: Kobra | I15: =H15/60+G15+F15*24 -> 0 | J15: =IF(D15<>"",C15/1000*VLOOKUP(D15,MATERIAIS!$B$3:$E$51,4,FALSE),0) -> 0 | K15: =IF(E15<>"",I15*VLOOKUP(E15,IMPRESSORAS!$B$3:$G$51,6,FALSE),0) -> 0 | L15: =IF(E15<>"",I15*$D$20*VLOOKUP(E15,IMPRESSORAS!$B$3:$G$51,5,FALSE),0) -> 0 | M15: =SUM(K15:L15) -> 0
B19: OUTROS
B20: Custo do kWh | C20: R$/kWh | D20: 0.9
B21: Taxa de falhas | C21: % | D21: 15
B23: CONSUMÍVEIS | D23: =SUM(D24:D31) -> 0
B24: Lixa | D24: 0
B25: Tinta | D25: 0

Sheet DESPESAS (FIXO)
E2: TOTAL DEPRECIAÇÃO DO IMOBILIZADO | H2: =SUM(H4:H52) -> 191.23333
B3: DEPESAS (FIXO) | C3: =SUM(C4:C52) -> 191.23333 | E3: ITEM | F3: DESPESA (R$) | G3: VIDA ÚTIL (ANOS) | H3: DEPRECIAÇÃO
B4: DEPRECIAÇÃO DO IMOBILIZADO | C4: =$H$2 -> 191.23333 | E4: Computador | F4: 8000 | G4: 5 | H4: =IF(G4>0,F4/(G4*12),0) -> 133.33333
B5: AGUA | E5: Monitor | F5: 2000 | G5: 5 | H5: =IF(G5>0,F5/(G5*12),0) -> 33.333333
B6: ALUGUEL E CONDOMÍNIO DO IMÓVEL | E6: Mesa | F6: 687 | G6: 5 | H6: =IF(G6>0,F6/(G6*12),0) -> 11.45
B7: ALUGUEL DE MAQUINETA | E7: Alicate | F7: 20 | G7: 1 | H7: =IF(G7>0,F7/(G7*12),0) -> 1.6666667
B8: ALUGUEL OUTROS | E8: Bancada | F8: 687 | G8: 5 | H8: =IF(G8>0,F8/(G8*12),0) -> 11.45
B9: ASSINATURA JORNAL | H9: =IF(G9>0,F9/(G9*12),0) -> 0
B10: CARTÓRIO | H10: =IF(G10>0,F10/(G10*12),0) -> 0
B11: CELULAR | H11: =IF(G11>0,F11/(G11*12),0) -> 0
B12: COMBUSTÍVEL | H12: =IF(G12>0,F12/(G12*12),0) -> 0
B13: CONSULTORIA | H13: =IF(G13>0,F13/(G13*12),0) -> 0
B14: CONTABILIDADE | H14: =IF(G14>0,F14/(G14*12),0) -> 0
B15: CORREIOS | H15: =IF(G15>0,F15/(G15*12),0) -> 0
B16: CURSOS E TREINAMENTO | H16: =IF(G16>0,F16/(G16*12),0) -> 0
H17: =IF(G17>0,F17/(G17*12),0) -> 0
B18: DOC/TED | H18: =IF(G18>0,F18/(G18*12),0) -> 0
B19: ENERGIA ELÉTRICA (SEM CONTAR A IMPRESSORA 3D) | H19: =IF(G19>0,F19/(G19*12),0) -> 0
B20: ESTACIONAMENTO | H20: =IF(G20>0,F20/(G20*12),0) -> 0
B21: FUNCIONÁRIOS CESTA BASICA | H21: =IF(G21>0,F21/(G21*12),0) -> 0
B22: FUNCIONÁRIOS FGTS | H22: =IF(G22>0,F22/(G22*12),0) -> 0
B23: FUNCIONÁRIOS FGTS MULTA | H23: =IF(G23>0,F23/(G23*12),0) -> 0
B24: FUNCIONÁRIOS INSS PARTE EMPRESA | H24: =IF(G24>0,F24/(G24*12),0) -> 0
B25: FUNCIONÁRIOS PLANO DE SAUDE | H25: =IF(G25>0,F25/(G25*12),0) -> 0
B26: FUNCIONÁRIOS RESCISÃO | H26: =IF(G26>0,F26/(G26*12),0) -> 0
B27: FUNCIONÁRIOS SALÁRIOS | H27: =IF(G27>0,F27/(G27*12),0) -> 0
B28: FUNCIONÁRIOS VT E VR | H28: =IF(G28>0,F28/(G28*12),0) -> 0
B29: FUNCIONÁRIOS 13º SALÁRIO E FÉRIAS (PREVISÃO) | H29: =IF(G29>0,F29/(G29*12),0) -> 0
... B50: TARIFAS DIVERSAS BANCOS | H50: =IF(G50>0,F50/(G50*12),0) -> 0
H51: =IF(G51>0,F51/(G51*12),0) -> 0
B52: TELEFONE | H52: =IF(G52>0,F52/(G52*12),0) -> 0

Sheet CUSTO HORA DE TRABALHO
B2: MÃO DE OBRA DIRETA OU CAPACIDADE PRODUTIVA | E2: CUSTO HORA DE TRABALHO
B3: Número de pessoas produtivas | C3: 1 | E3: DESPESAS FIXAS | F3: R$ | G3: ='DESPESAS (FIXO)'!C3 -> 191.23333
B4: Horas diárias máximas produtivas (média por pessoa) | C4: 8 | E4: CAPACIDADE PRODUTIVA DISPONÍVEL | F4: Horas | G4: ='CUSTO HORA DE TRABALHO'!C8 -> 149.6
B5: Dias trabalhados no mês (média por pessoa) | C5: 22 | E5: CUSTO HORA | F5: R$ | G5: =G3/G4 -> 1.2782977
B6: HORAS PRODUTIVAS MÁXIMAS NO MÊS | C6: =C3*C4*C5 -> 176
B7: % de produtividade | C7: 0.85
B8: Total de horas produtivas ou disponibilizadas no mês | C8: =C6*C7 -> 149.6

Sheet TOTAL CUSTO HORAS TRABALHADAS
B2: TOTAL DO CUSTO DO TRABALHO | C2: =C3*C4 -> 0.36218434
B3: CUSTO HORA CALCULADO | C3: ='CUSTO HORA DE TRABALHO'!G5 -> 1.2782977
B4: HORAS TRABALHADOS NO SERVIÇO | C4: =SUM(C6:C29)/60 -> 0.28333333
B5: SERVIÇO | C5: TEMPO (MINUTOS)
B6: DOWNLOAD | C6: 2
B7: PREPARAÇÃO DO MODELO (AJUSTES, CAD...) | C7: 0
B8: FATIAMENTO (SUPORTES, PARÂMETROS...) | C8: 2
B9: TROCA DE MATERIAL | C9: 5
B10: TRANSFERÊNCIA E INÍCIO | C10: 7
B11: REMOÇÃO DA PEÇAS DA MESA | C11: 1
B12: REMOÇÃO DO SUPORTE
B13: ACABAMENTO (LIXAMENTO, REBARBAÇÃO...)

Sheet PREÇO DE VENDA
B2: CÁLCULO DO PREÇO DE VENDA À VISTA | F2: =B15 -> MATERIAL (FILAMENTO) | G2: =C15 -> 6.345
F3: =B16 -> DEPRECIAÇÃO DA IMPRESSORA 3D | G3: =C16 -> 3.575
B4: ÍNDICES DE COMERCIALIZAÇÃO | C4: =SUM(C5:C10) -> 12.606302 | D4: =SUM(D5:D10) -> 0.5 | F4: =B17 -> ELETRICIDADE | G4: =C17 -> 0.4875
B5: IMPOSTOS | C5: =$C$24*D5 -> 0 | D5: 0 | F5: =B18 -> CONSUMÍVEIS | G5: =C18 -> 0
B6: TAXA DE VENDA ONLINE | C6: =$C$24*D6 -> 0 | D6: 0 | F6: =B19 -> FALHAS DE IMPRESSÃO | G6: =C19 -> 1.8366176
B7: TAXA DE VENDA POR CARTÃO | C7: =$C$24*D7 -> 0 | D7: 0 | F7: =B20 -> CUSTO HORAS TRABALHADAS | G7: =C20 -> 0.36218434
B8: RESERVADO | C8: =$C$24*D8 -> 0 | D8: 0 | F8: TAXAS | G8: =SUM(C5:C9) -> 0
B9: RESERVADO | C9: =$C$24*D9 -> 0 | D9: 0 | F9: =B10 -> LUCRO | G9: =C10 -> 12.606302
B10: LUCRO | C10: =$C$24*D10 -> 12.606302 | D10: 0.5
B12: MARK UP MULTIPLICADOR | C12: =1/(1-D4) -> 2 | D12: =C12 -> 2
B14: TOTAL CUSTO IMPRESSÃO 3D | C14: =SUM(C15:C20) -> 12.606302 | D14: =SUM(D15:D20) -> 0.5
B15: MATERIAL (FILAMENTO) | C15: ='CUSTO DE IMPRESSÃO 3D'!J4 -> 6.345 | D15: =C15/($C$24) -> 0.25165984
B16: DEPRECIAÇÃO DA IMPRESSORA 3D | C16: ='CUSTO DE IMPRESSÃO 3D'!K4 -> 3.575 | D16: =C16/($C$24) -> 0.14179416
B17: ELETRICIDADE | C17: ='CUSTO DE IMPRESSÃO 3D'!L4 -> 0.4875 | D17: =C17/($C$24) -> 0.019335567
B18: CONSUMÍVEIS | C18: ='CUSTO DE IMPRESSÃO 3D'!D23 -> 0 | D18: =C18/($C$24) -> 0
B19: FALHAS DE IMPRESSÃO | C19: ='CUSTO DE IMPRESSÃO 3D'!O4-'CUSTO DE IMPRESSÃO 3D'!N4 -> 1.8366176 | D19: =C19/($C$24) -> 0.072845219
B20: CUSTO HORAS TRABALHADAS | C20: ='TOTAL CUSTO HORAS TRABALHADAS'!C2 -> 0.36218434 | D20: =C20/($C$24) -> 0.01436521
B22: FRETE / ENTREGA | C22: 0
B24: PREÇO DE VENDA À VISTA | C24: =C14*'PREÇO DE VENDA'!C12 -> 25.212604
B25: PREÇO DE VENDA À VISTA + FRETE | C25: =C24+C22 -> 25.212604
